segmentation_sust/__init__.py
segmentation_sust/__version__.py
segmentation_sust/base/__init__.py
segmentation_sust/base/heads.py
segmentation_sust/base/initialization.py
segmentation_sust/base/model.py
segmentation_sust/base/modules.py
segmentation_sust/deeplabv3/__init__.py
segmentation_sust/deeplabv3/decoder.py
segmentation_sust/deeplabv3/model.py
segmentation_sust/encoders/__init__.py
segmentation_sust/encoders/_base.py
segmentation_sust/encoders/_preprocessing.py
segmentation_sust/encoders/_utils.py
segmentation_sust/encoders/densenet.py
segmentation_sust/encoders/dpn.py
segmentation_sust/encoders/efficientnet.py
segmentation_sust/encoders/inceptionresnetv2.py
segmentation_sust/encoders/inceptionv4.py
segmentation_sust/encoders/mobilenet.py
segmentation_sust/encoders/resnet.py
segmentation_sust/encoders/senet.py
segmentation_sust/encoders/timm_efficientnet.py
segmentation_sust/encoders/timm_regnet.py
segmentation_sust/encoders/timm_res2net.py
segmentation_sust/encoders/timm_resnest.py
segmentation_sust/encoders/timm_sknet.py
segmentation_sust/encoders/vgg.py
segmentation_sust/encoders/xception.py
segmentation_sust/fpn/__init__.py
segmentation_sust/fpn/decoder.py
segmentation_sust/fpn/model.py
segmentation_sust/linknet/__init__.py
segmentation_sust/linknet/decoder.py
segmentation_sust/linknet/model.py
segmentation_sust/pan/__init__.py
segmentation_sust/pan/decoder.py
segmentation_sust/pan/model.py
segmentation_sust/pspnet/__init__.py
segmentation_sust/pspnet/decoder.py
segmentation_sust/pspnet/model.py
segmentation_sust/unet/__init__.py
segmentation_sust/unet/decoder.py
segmentation_sust/unet/model.py
segmentation_sust/unetplusplus/__init__.py
segmentation_sust/unetplusplus/decoder.py
segmentation_sust/unetplusplus/model.py
segmentation_sust/utils/__init__.py
segmentation_sust/utils/base.py
segmentation_sust/utils/functional.py
segmentation_sust/utils/losses.py
segmentation_sust/utils/meter.py
segmentation_sust/utils/metrics.py
segmentation_sust/utils/train.py
segmentation_sust-0.1.3.dist-info/LICENSE
segmentation_sust-0.1.3.dist-info/METADATA
segmentation_sust-0.1.3.dist-info/WHEEL
segmentation_sust-0.1.3.dist-info/top_level.txt
segmentation_sust-0.1.3.dist-info/RECORD
